README.txt
setup.cfg
setup.py
collective/__init__.py
collective.autopermission.egg-info/PKG-INFO
collective.autopermission.egg-info/SOURCES.txt
collective.autopermission.egg-info/dependency_links.txt
collective.autopermission.egg-info/entry_points.txt
collective.autopermission.egg-info/namespace_packages.txt
collective.autopermission.egg-info/not-zip-safe
collective.autopermission.egg-info/requires.txt
collective.autopermission.egg-info/top_level.txt
collective/autopermission/__init__.py
collective/autopermission/configure.zcml
collective/autopermission/permissions.py
docs/HISTORY.txt
docs/INSTALL.txt