Metadata-Version: 1.0
Name: collective.autopermission
Version: 1.0b2
Summary: Create permissions in Zope 2 on demand when a <permission /> directive is used
Home-page: http://pypi.python.org/pypi/collective.autopermission
Author: Martin Aspeli
Author-email: optilude@gmail.com
License: BSD
Keywords: zope permission
Platform: UNKNOWN
Classifier: Framework :: Plone
Classifier: Programming Language :: Python
Classifier: Topic :: Software Development :: Libraries :: Python Modules
